[
  {
    "id": "nnrawqh5z",
    "cn": "山梨县立科学馆展望台",
    "name": "山梨県立科学館展望テラス",
    "image": "https://image.xinu.ink/pic/data/6019/images/nnrawqh5z_1744480914393.jpg",
    "ep": 1,
    "s": 1279,
    "geo": [
      35.6688,
      138.5807
    ]
  },
  {
    "id": "ulrdcvgf3",
    "cn": "山梨县立科学馆展望台1",
    "name": "山梨県立科学館展望テラス1",
    "image": "https://image.xinu.ink/pic/data/6019/images/ulrdcvgf3_1744481878396.jpg",
    "ep": 1,
    "s": 1174,
    "geo": [
      35.6689,
      138.5806
    ],
    "origin": "Anitabi@月即别",
    "originURL": "https://anitabi.cn/"
  },
  {
    "id": "ulqzj2r7y",
    "cn": "山梨县立科学馆 延时摄影1",
    "name": "山梨県立科学館",
    "image": "https://image.xinu.ink/pic/data/6019/images/ulqzj2r7y_1744480951264.jpg",
    "ep": 1,
    "s": 1248,
    "geo": [
      35.6688,
      138.5807
    ],
    "origin": "Anitabi@月即别",
    "originURL": "https://anitabi.cn/"
  },
  {
    "id": "ulqzkap8i",
    "cn": "山梨县立科学馆 延时摄影2",
    "name": "山梨県立科学館",
    "image": "https://image.xinu.ink/pic/data/6019/images/ulqzkap8i_1744480964444.jpg",
    "ep": 1,
    "s": 1322,
    "geo": [
      35.6688,
      138.5807
    ],
    "origin": "Anitabi@月即别",
    "originURL": "https://anitabi.cn/"
  },
  {
    "id": "ulqw3kg6t",
    "cn": "山梨县立科学馆 阶梯",
    "name": "山梨県立科学館 階段",
    "image": "https://image.xinu.ink/pic/data/6019/images/ulqw3kg6t-1744480781319.jpg",
    "ep": 1,
    "s": 1106,
    "geo": [
      35.6699,
      138.5806
    ],
    "origin": "Anitabi@月即别",
    "originURL": "https://anitabi.cn/"
  },
  {
    "id": "uu4s5tbi2",
    "cn": "山梨县立科学馆",
    "name": "山梨県立科学館",
    "image": "https://image.xinu.ink/pic/data/6019/images/uu4s5tbi2_1745137908846.jpg",
    "ep": 1,
    "s": 1117,
    "geo": [
      35.6694,
      138.5803
    ],
    "origin": "Anitabi@concert",
    "originURL": "https://anitabi.cn/"
  },
  {
    "id": "ulrac72p8",
    "cn": "山梨县立科学馆前",
    "name": "山梨県立科学館前",
    "image": "https://image.xinu.ink/pic/data/6019/images/ulrac72p8_1744481655085.jpg",
    "ep": 1,
    "s": 1103,
    "geo": [
      35.67,
      138.5804
    ],
    "origin": "Anitabi@月即别",
    "originURL": "https://anitabi.cn/"
  },
  {
    "id": "ulpulzi4c",
    "name": "笛吹川水果公园",
    "image": "https://image.xinu.ink/pic/data/6019/images/ulpulzi4c_1745297514718.jpg",
    "ep": 1,
    "s": 1022,
    "geo": [
      35.7027,
      138.6639
    ],
    "origin": "Anitabi@月即别",
    "originURL": "https://anitabi.cn/"
  },
  {
    "id": "ulpyv78d1",
    "cn": "甲府市政府",
    "name": "甲府市役所",
    "image": "https://image.xinu.ink/pic/data/6019/images/ulpyv78d1_1745297703111.jpg",
    "ep": 1,
    "s": 1026,
    "geo": [
      35.662,
      138.5683
    ],
    "origin": "Anitabi@月即别",
    "originURL": "https://anitabi.cn/"
  },
  {
    "id": "nrfwoorcn",
    "cn": "舞鹤城公园",
    "name": "舞鶴城公園",
    "image": "https://image.xinu.ink/pic/data/6019/images/nrfwoorcn_1745083441401.jpg",
    "ep": 2,
    "s": 516,
    "geo": [
      35.6642,
      138.5711
    ]
  },
  {
    "id": "utlac7uey",
    "cn": "舞鹤城公园 南口",
    "name": "舞鶴城公園 南口",
    "image": "https://image.xinu.ink/pic/data/6019/images/utlac7uey_1745095445543_c16v9.jpg",
    "ep": 2,
    "s": 512,
    "geo": [
      35.6643,
      138.5712
    ],
    "origin": "Anitabi@concert",
    "originURL": "https://anitabi.cn/"
  },
  {
    "id": "utljl7m65",
    "cn": "舞鹤城公园 西眺",
    "name": "舞鶴城公園",
    "image": "https://image.xinu.ink/pic/data/6019/images/utljl7m65_1745096024751_c16v9.jpg",
    "ep": 2,
    "s": 574,
    "geo": [
      35.6652,
      138.5712
    ],
    "origin": "Anitabi@concert",
    "originURL": "https://anitabi.cn/"
  },
  {
    "id": "utl6cdh3p",
    "cn": "舞鹤城公园 航拍",
    "name": "舞鶴城公園 空撮",
    "image": "https://image.xinu.ink/pic/data/6019/images/utl6cdh3p_1745095200309_c16v9.jpg",
    "ep": 2,
    "s": 586,
    "geo": [
      35.6652,
      138.5713
    ],
    "origin": "Anitabi@concert",
    "originURL": "https://anitabi.cn/"
  },
  {
    "id": "utkzo6enf",
    "cn": "舞鹤城公园 南眺",
    "name": "舞鶴城公園",
    "image": "https://image.xinu.ink/pic/data/6019/images/utkzo6enf_1745095150487_c16v9.jpg",
    "ep": 2,
    "s": 596,
    "geo": [
      35.6652,
      138.5713
    ],
    "origin": "Anitabi@concert",
    "originURL": "https://anitabi.cn/"
  },
  {
    "id": "utl534dzd",
    "cn": "舞鹤城公园 东眺",
    "name": "舞鶴城公園",
    "image": "https://image.xinu.ink/pic/data/6019/images/utl534dzd_1745095152077_c16v9.jpg",
    "ep": 2,
    "s": 601,
    "geo": [
      35.6653,
      138.5712
    ],
    "origin": "Anitabi@concert",
    "originURL": "https://anitabi.cn/"
  },
  {
    "id": "uu56kt1w1",
    "name": "舞鶴城公園",
    "image": "https://image.xinu.ink/pic/data/6019/images/uu56kt1w1_1745138749875_c16v9.jpg",
    "ep": 2,
    "s": 687,
    "geo": [
      35.6652,
      138.5713
    ],
    "origin": "Anitabi@concert",
    "originURL": "https://anitabi.cn/"
  },
  {
    "id": "utldb3qlg",
    "cn": "甲府城 鉄門",
    "name": "",
    "image": "https://image.xinu.ink/pic/data/6019/images/utldb3qlg_1745095796249_c16v9.jpg",
    "ep": 2,
    "s": 552,
    "geo": [
      35.665,
      138.5706
    ],
    "origin": "Anitabi@concert",
    "originURL": "https://anitabi.cn/"
  },
  {
    "id": "utlf83noq",
    "cn": "甲府城迹 阶梯",
    "name": "甲府城跡 階段",
    "image": "https://image.xinu.ink/pic/data/6019/images/utlf83noq_1745095802910_c16v9.jpg",
    "ep": 2,
    "s": 563,
    "geo": [
      35.6653,
      138.5712
    ],
    "origin": "Anitabi@concert",
    "originURL": "https://anitabi.cn/"
  },
  {
    "id": "utmxe4k7e",
    "cn": "甲府城迹 阶梯2",
    "name": "甲府城跡 階段2",
    "image": "https://image.xinu.ink/pic/data/6019/images/utmxe4k7e_1745099063491.jpg",
    "ep": 2,
    "s": 565,
    "geo": [
      35.6653,
      138.5712
    ],
    "origin": "Anitabi@Xenon丸子头",
    "originURL": "https://anitabi.cn/"
  },
  {
    "id": "utert5rz3",
    "name": "東沢大橋",
    "image": "https://image.xinu.ink/pic/data/6019/images/utert5rz3_1745081757528_c16v9.jpg",
    "ep": 2,
    "s": 1118,
    "geo": [
      35.9321,
      138.4139
    ],
    "origin": "Anitabi@concert",
    "originURL": "https://anitabi.cn/"
  },
  {
    "id": "utfln0nb6",
    "cn": "pauls餐厅",
    "name": 24,
    "image": "https://image.xinu.ink/pic/data/6019/images/utfln0nb6_1745083066965.jpg",
    "ep": 2,
    "s": 1221,
    "geo": [
      36.0351,
      138.2602
    ],
    "origin": "Anitabi@蛙壶真君",
    "originURL": "https://anitabi.cn/"
  },
  {
    "id": "ulp4dtzjo",
    "name": "石和温泉駅",
    "image": "https://image.xinu.ink/pic/data/6019/images/ulp4dtzjo-1744476887136.jpg",
    "ep": 1,
    "geo": [
      35.6574,
      138.6352
    ],
    "origin": "Anitabi@月即别",
    "originURL": "https://anitabi.cn/"
  },
  {
    "id": "ulr49y96z",
    "name": "山道",
    "image": "https://image.xinu.ink/pic/data/6019/images/ulr49y96z_1744481264378.jpg",
    "ep": 1,
    "geo": [
      35.67,
      138.5876
    ],
    "origin": "Anitabi@月即别",
    "originURL": "https://anitabi.cn/"
  },
  {
    "id": "uteo2nsvp",
    "cn": "七贤",
    "name": "",
    "image": "https://image.xinu.ink/pic/data/6019/images/uteo2nsvp_1745081193681.jpg",
    "ep": 2,
    "geo": [
      35.8085,
      138.3427
    ],
    "origin": "Anitabi@LovelySummer Channel",
    "originURL": "https://anitabi.cn/"
  },
  {
    "id": "utezttpvv",
    "name": "まきば​公園​",
    "image": "https://image.xinu.ink/pic/data/6019/images/utezttpvv_1745081748975_c16v9.jpg",
    "ep": 2,
    "geo": [
      35.9235,
      138.4078
    ],
    "origin": "Anitabi@concert",
    "originURL": "https://anitabi.cn/"
  },
  {
    "id": "utfblsyl2",
    "name": "レスト​ハウス​ふるさと",
    "image": "https://image.xinu.ink/pic/data/6019/images/utfblsyl2_1745082458216_c16v9.jpg",
    "ep": 2,
    "geo": [
      36.0641,
      138.3927
    ],
    "origin": "Anitabi@concert",
    "originURL": "https://anitabi.cn/"
  },
  {
    "id": "uu4nj38a2",
    "name": "新倉山浅間公園",
    "image": "https://image.xinu.ink/pic/data/6019/images/uu4nj38a2_1745137596144_c16v9.jpg",
    "ep": "OP1",
    "geo": [
      35.5009,
      138.8016
    ],
    "origin": "Anitabi@concert",
    "originURL": "https://anitabi.cn/"
  },
  {
    "id": "uu5egbfcr",
    "name": "昇仙峡ライン 長潭橋",
    "image": "https://image.xinu.ink/pic/data/6019/images/uu5egbfcr_1745139231691_c16v9.jpg",
    "ep": "OP1",
    "geo": [
      35.7258,
      138.5488
    ],
    "origin": "Anitabi@concert",
    "originURL": "https://anitabi.cn/"
  },
  {
    "id": "uu5iattr3",
    "name": "御坂隧道",
    "image": "https://image.xinu.ink/pic/data/6019/images/uu5iattr3_1745139472275_c16v9.jpg",
    "ep": "OP1",
    "geo": [
      35.5564,
      138.7837
    ],
    "origin": "Anitabi@concert",
    "originURL": "https://anitabi.cn/"
  },
  {
    "id": "v1cwr5vrg",
    "cn": "食事・喫茶ガロ",
    "name": "軽食喫茶ガロ",
    "image": "https://image.xinu.ink/pic/data/6019/images/v1cwr5vrg_1745704139353_c16v9.jpg",
    "ep": 3,
    "s": 1125,
    "geo": [
      35.7433,
      137.889
    ],
    "origin": "Anitabi@concert",
    "originURL": "https://anitabi.cn/"
  },
  {
    "id": "v1uivpvit",
    "cn": "超级神冈探测器",
    "name": "スーパーカミオカンデ",
    "image": "https://image.xinu.ink/pic/data/6019/images/v1uivpvit-1745742597673.jpg",
    "ep": 3,
    "s": 149,
    "geo": [
      36.4268,
      137.3101
    ]
  },
  {
    "id": "v3a2cr6ju",
    "cn": "黑部水坝",
    "name": "黒部ダム",
    "image": "https://image.xinu.ink/pic/data/6019/images/v3a2cr6ju_1745854662395.jpg",
    "ep": 3,
    "s": 141,
    "geo": [
      36.5661,
      137.662
    ],
    "origin": "Anitabi@Xenon丸子头",
    "originURL": "https://anitabi.cn/"
  },
  {
    "id": "v3agj5uv5",
    "cn": "甲府站 站台",
    "name": "甲府駅 ホーム",
    "image": "https://image.xinu.ink/pic/data/6019/images/v3agj5uv5_1745855531167.jpg",
    "ep": 1,
    "s": 619,
    "geo": [
      35.6672,
      138.569
    ],
    "origin": "Anitabi@Xenon丸子头",
    "originURL": "https://anitabi.cn/"
  },
  {
    "id": "v5l7j4r1t",
    "cn": "身延站前",
    "name": "身延駅前",
    "image": "https://image.xinu.ink/pic/data/6019/images/v5l7j4r1t_1746035691816.jpg",
    "ep": 3,
    "s": 643,
    "geo": [
      35.3616,
      138.4524
    ],
    "origin": "Anitabi@Xenon丸子头",
    "originURL": "https://anitabi.cn/"
  },
  {
    "id": "v5lfcrmgs",
    "cn": "首都圈外郭放水路",
    "name": "首都圏外郭放水路",
    "image": "https://image.xinu.ink/pic/data/6019/images/v5lfcrmgs_1746036173856.jpg",
    "ep": 3,
    "s": 146,
    "geo": [
      35.996,
      139.8105
    ],
    "origin": "Anitabi@Xenon丸子头",
    "originURL": "https://anitabi.cn/"
  },
  {
    "id": "v1dg206dz",
    "name": "峠の茶屋",
    "image": "https://image.xinu.ink/pic/data/6019/images/v1dg206dz_1745705321334_c16v9.jpg",
    "ep": 3,
    "geo": [
      35.9767,
      138.1299
    ],
    "origin": "Anitabi@concert",
    "originURL": "https://anitabi.cn/"
  },
  {
    "id": "v1dns51vy",
    "name": "ファミリー​マート\n長坂​駅前​店",
    "image": "https://image.xinu.ink/pic/data/6019/images/v1dns51vy_1745705786761_c16v9.jpg",
    "ep": 3,
    "geo": [
      35.8281,
      138.3692
    ],
    "origin": "Anitabi@concert",
    "originURL": "https://anitabi.cn/"
  },
  {
    "id": "v13uh8yt2",
    "cn": "本栖湖",
    "name": "本栖湖",
    "image": "https://image.xinu.ink/pic/data/6019/images/v13uh8yt2_1745687321409.jpg",
    "ep": 3,
    "geo": [
      35.474,
      138.5756
    ],
    "origin": "Anitabi@LovelySummer Channel",
    "originURL": "https://anitabi.cn/"
  },
  {
    "id": "v13wxc5te",
    "cn": "本栖湖厕所",
    "name": "本栖湖 公衆トイレ",
    "image": "https://image.xinu.ink/pic/data/6019/images/v13wxc5te_1745687354238.jpg",
    "ep": 3,
    "geo": [
      35.4741,
      138.5742
    ],
    "origin": "Anitabi@LovelySummer Channel",
    "originURL": "https://anitabi.cn/"
  },
  {
    "id": "v13x64wz3",
    "name": "セントラル​ロッジ​浩​庵",
    "image": "https://image.xinu.ink/pic/data/6019/images/v13x64wz3_1745687358262.jpg",
    "ep": 3,
    "geo": [
      35.4736,
      138.5734
    ],
    "origin": "Anitabi@LovelySummer Channel",
    "originURL": "https://anitabi.cn/"
  },
  {
    "id": "v13uxw4xo",
    "cn": "浩​庵露营地",
    "name": 51,
    "image": "https://image.xinu.ink/pic/data/6019/images/v13uxw4xo_1745687327582.jpg",
    "ep": 3,
    "geo": [
      35.473,
      138.5751
    ],
    "origin": "Anitabi@LovelySummer Channel",
    "originURL": "https://anitabi.cn/"
  },
  {
    "id": "v16ptparn",
    "cn": "朝雾高原山麓露营场",
    "name": "ふもとっぱらキャンプ場",
    "image": "https://image.xinu.ink/pic/data/6019/images/v16ptparn_1745690670404.jpg",
    "ep": 3,
    "geo": [
      35.4,
      138.563
    ],
    "origin": "Anitabi@月即别",
    "originURL": "https://anitabi.cn/"
  },
  {
    "id": "v149azlhs",
    "cn": "芝麻凛的家",
    "name": "下部水防倉庫",
    "image": "https://image.xinu.ink/pic/data/6019/images/v149azlhs_1745687566794.jpg",
    "ep": 3,
    "geo": [
      35.4791,
      138.5271
    ],
    "origin": "Anitabi@LovelySummer Channel",
    "originURL": "https://anitabi.cn/"
  },
  {
    "id": "v14bq74w2",
    "name": "内船駅内",
    "image": "https://image.xinu.ink/pic/data/6019/images/v14bq74w2_1745688753350.jpg",
    "ep": 3,
    "geo": [
      35.2815,
      138.4651
    ],
    "origin": "Anitabi@LovelySummer Channel",
    "originURL": "https://anitabi.cn/"
  },
  {
    "id": "v1bea1f91",
    "name": "内船駅",
    "image": "https://image.xinu.ink/pic/data/6019/images/v1bea1f91_1745700847198_c16v9.jpg",
    "ep": 3,
    "geo": [
      35.2814,
      138.4649
    ],
    "origin": "Anitabi@concert",
    "originURL": "https://anitabi.cn/"
  },
  {
    "id": "v14cxp8i2",
    "cn": "南部桥",
    "name": "南部橋",
    "image": "https://image.xinu.ink/pic/data/6019/images/v14cxp8i2_1745687511354.jpg",
    "ep": 3,
    "geo": [
      35.2819,
      138.4599
    ],
    "origin": "Anitabi@LovelySummer Channel",
    "originURL": "https://anitabi.cn/"
  },
  {
    "id": "v14fqywys",
    "cn": "抚子的家",
    "name": 63,
    "image": "https://image.xinu.ink/pic/data/6019/images/v14fqywys_1745687517660.jpg",
    "ep": 3,
    "geo": [
      35.2824,
      138.4564
    ],
    "origin": "Anitabi@LovelySummer Channel",
    "originURL": "https://anitabi.cn/"
  },
  {
    "id": "v15cj8u86",
    "cn": "水明庄露营地",
    "name": "水明​荘​キャンプ場",
    "image": "https://image.xinu.ink/pic/data/6019/images/v15cj8u86_1745687649640.jpg",
    "ep": 3,
    "geo": [
      35.5303,
      138.5187
    ],
    "origin": "Anitabi@LovelySummer Channel",
    "originURL": "https://anitabi.cn/"
  },
  {
    "id": "v14nip4rb",
    "cn": "南アルプス林道夜叉神ゲート 警備員小屋",
    "name": 63,
    "image": "https://image.xinu.ink/pic/data/6019/images/v14nip4rb_1745687683587.jpg",
    "ep": 3,
    "geo": [
      35.6353,
      138.3439
    ],
    "origin": "Anitabi@LovelySummer Channel",
    "originURL": "https://anitabi.cn/"
  },
  {
    "id": "v1bu4ugk0",
    "cn": "南アルプス林道夜叉神",
    "name": 63,
    "image": "https://image.xinu.ink/pic/data/6019/images/v1bu4ugk0_1745701789873_c16v9.jpg",
    "ep": 3,
    "geo": [
      35.6341,
      138.3496
    ],
    "origin": "Anitabi@concert",
    "originURL": "https://anitabi.cn/"
  },
  {
    "id": "v14rr1e18",
    "cn": "诹访湖休息站",
    "name": 63,
    "image": "https://image.xinu.ink/pic/data/6019/images/v14rr1e18_1745687746831.jpg",
    "ep": 3,
    "geo": [
      36.0267,
      138.0773
    ],
    "origin": "Anitabi@LovelySummer Channel",
    "originURL": "https://anitabi.cn/"
  },
  {
    "id": "v1dxicjt3",
    "cn": "冈谷JCT",
    "name": "岡谷JCT",
    "image": "https://image.xinu.ink/pic/data/6019/images/v1dxicjt3_1745706357406_c16v9.jpg",
    "ep": 3,
    "geo": [
      36.0522,
      138.0456
    ],
    "origin": "Anitabi@concert",
    "originURL": "https://anitabi.cn/"
  },
  {
    "id": "v14t013ho",
    "cn": "ハイウェイ温泉",
    "name": 63,
    "image": "https://image.xinu.ink/pic/data/6019/images/v14t013ho_1745687857167.jpg",
    "ep": 3,
    "geo": [
      36.0263,
      138.0785
    ],
    "origin": "Anitabi@LovelySummer Channel",
    "originURL": "https://anitabi.cn/"
  },
  {
    "id": "v1d5gmxn0",
    "name": "アポロ​ステーション​諏訪湖​サービス​エリア​上り​SS",
    "image": "https://image.xinu.ink/pic/data/6019/images/v1d5gmxn0_1745704677130_c16v9.jpg",
    "ep": 3,
    "geo": [
      36.0258,
      138.0784
    ],
    "origin": "Anitabi@concert",
    "originURL": "https://anitabi.cn/"
  },
  {
    "id": "v14uln9zj",
    "cn": "松本城",
    "name": 63,
    "image": "https://image.xinu.ink/pic/data/6019/images/v14uln9zj_1745687906723.jpg",
    "ep": 3,
    "geo": [
      36.2378,
      137.9696
    ],
    "origin": "Anitabi@LovelySummer Channel",
    "originURL": "https://anitabi.cn/"
  },
  {
    "id": "v14wr10fq",
    "cn": "阵马形山露营场",
    "name": "陣馬形山キャンプ場",
    "image": "https://image.xinu.ink/pic/data/6019/images/v14wr10fq_1745687992295.jpg",
    "ep": 3,
    "geo": [
      35.6729,
      137.9833
    ],
    "origin": "Anitabi@LovelySummer Channel",
    "originURL": "https://anitabi.cn/"
  },
  {
    "id": "v150v1g8n",
    "cn": "光前寺",
    "name": 63,
    "image": "https://image.xinu.ink/pic/data/6019/images/v150v1g8n_1745688099094.jpg",
    "ep": 3,
    "geo": [
      35.7348,
      137.8955
    ],
    "origin": "Anitabi@LovelySummer Channel",
    "originURL": "https://anitabi.cn/"
  },
  {
    "id": "v17ayvnp8",
    "name": "軽食喫茶ガロ",
    "image": "https://image.xinu.ink/pic/data/6019/images/v17ayvnp8-1745691941951.jpg",
    "ep": 3,
    "geo": [
      35.7432,
      137.889
    ],
    "origin": "Anitabi@月即别",
    "originURL": "https://anitabi.cn/"
  },
  {
    "id": "v1czctx6v",
    "name": "うるおいとふれあいのある水辺",
    "image": "https://image.xinu.ink/pic/data/6019/images/v1czctx6v_1745704278524_c16v9.jpg",
    "ep": 3,
    "geo": [
      35.7448,
      137.8886
    ],
    "origin": "Anitabi@concert",
    "originURL": "https://anitabi.cn/"
  },
  {
    "id": "v17ntmtjm",
    "name": "高ボッチ 牧場",
    "image": "https://image.xinu.ink/pic/data/6019/images/v17ntmtjm_1745692692039.jpg",
    "ep": 3,
    "geo": [
      36.1337,
      138.0351
    ],
    "origin": "Anitabi@月即别",
    "originURL": "https://anitabi.cn/"
  },
  {
    "id": "v15ncwfcu",
    "cn": "アルプス連峰パノラマ展望台",
    "name": 63,
    "image": "https://image.xinu.ink/pic/data/6019/images/v15ncwfcu_1745688318538.jpg",
    "ep": 3,
    "geo": [
      36.1351,
      138.0373
    ],
    "origin": "Anitabi@LovelySummer Channel",
    "originURL": "https://anitabi.cn/"
  },
  {
    "id": "v1806od0d",
    "name": "高ボッチスカイライン",
    "image": "https://image.xinu.ink/pic/data/6019/images/v1806od0d_1745693453697.jpg",
    "ep": 3,
    "geo": [
      36.1397,
      138.0403
    ],
    "origin": "Anitabi@月即别",
    "originURL": "https://anitabi.cn/"
  },
  {
    "id": "v18555fx6",
    "name": "鉢伏山道",
    "image": "https://image.xinu.ink/pic/data/6019/images/v18555fx6_1745693746075.jpg",
    "ep": 3,
    "geo": [
      36.1678,
      138.0575
    ],
    "origin": "Anitabi@月即别",
    "originURL": "https://anitabi.cn/"
  },
  {
    "id": "v153wvs6f",
    "cn": "钵伏山展望台",
    "name": "鉢伏山展望台",
    "image": "https://image.xinu.ink/pic/data/6019/images/v153wvs6f_1745688350129.jpg",
    "ep": 3,
    "geo": [
      36.1652,
      138.0576
    ],
    "origin": "Anitabi@LovelySummer Channel",
    "originURL": "https://anitabi.cn/"
  },
  {
    "id": "v15q9usgv",
    "cn": "片倉館",
    "name": 63,
    "image": "https://image.xinu.ink/pic/data/6019/images/v15q9usgv_1745688489915.jpg",
    "ep": 3,
    "geo": [
      36.048,
      138.1131
    ],
    "origin": "Anitabi@LovelySummer Channel",
    "originURL": "https://anitabi.cn/"
  },
  {
    "id": "v17tsxamc",
    "name": "霧の駅前",
    "image": "https://image.xinu.ink/pic/data/6019/images/v17tsxamc_1745693071295.jpg",
    "ep": 3,
    "geo": [
      36.0972,
      138.1681
    ],
    "origin": "Anitabi@月即别",
    "originURL": "https://anitabi.cn/"
  },
  {
    "id": "v1bbeocfj",
    "name": "ころぼっ​くる​ひゅっ​て",
    "image": "https://image.xinu.ink/pic/data/6019/images/v1bbeocfj_1745700659455_c16v9.jpg",
    "ep": 3,
    "geo": [
      36.1047,
      138.1878
    ],
    "origin": "Anitabi@concert",
    "originURL": "https://anitabi.cn/"
  },
  {
    "id": "utlmb3kw9",
    "cn": "舞鹤城公园",
    "name": "舞鶴城公園",
    "image": "https://image.xinu.ink/pic/data/6019/images/utlmb3kw9_1745096170278_c16v9.jpg",
    "ep": 2,
    "s": 515,
    "geo": [
      35.6652,
      138.5709
    ],
    "origin": "Anitabi@concert",
    "originURL": "https://anitabi.cn/"
  },
  {
    "id": "uteyn7bmr",
    "cn": "七贤",
    "name": 13,
    "image": "https://image.xinu.ink/pic/data/6019/images/uteyn7bmr_1745081665708.jpg",
    "ep": 2,
    "s": 892,
    "geo": [
      35.8085,
      138.3428
    ],
    "origin": "Anitabi@LovelySummer Channel",
    "originURL": "https://anitabi.cn/"
  },
  {
    "id": "uu4u0e42h",
    "name": "東沢大橋",
    "image": "https://image.xinu.ink/pic/data/6019/images/uu4u0e42h_1745138006263_c16v9.jpg",
    "ep": 2,
    "s": 1115,
    "geo": [
      35.9321,
      138.4139
    ],
    "origin": "Anitabi@concert",
    "originURL": "https://anitabi.cn/"
  },
  {
    "id": "2eexp7",
    "cn": "八ヶ岳食工房",
    "name": 219,
    "image": "https://image.xinu.ink/pic/data/6019/images/2eexp7_1747155505798.jpg",
    "ep": 5,
    "geo": [
      35.9704,
      138.2658
    ],
    "origin": "Anitabi@LovelySummer Channel",
    "originURL": "https://anitabi.cn/"
  },
  {
    "id": "v8uldogs5",
    "cn": "甲府站 南",
    "name": "甲府駅",
    "image": "https://image.xinu.ink/pic/data/6019/images/v8uldogs5_1746291153655.jpg",
    "ep": 4,
    "geo": [
      35.6664,
      138.5678
    ],
    "origin": "Anitabi@LovelySummer Channel",
    "originURL": "https://anitabi.cn/"
  },
  {
    "id": "v8upms6jg",
    "name": "甲府駅南口駅前広場",
    "image": "https://image.xinu.ink/pic/data/6019/images/v8upms6jg_1746291415451.jpg",
    "ep": 4,
    "geo": [
      35.6668,
      138.5679
    ],
    "origin": "Anitabi@LovelySummer Channel",
    "originURL": "https://anitabi.cn/"
  },
  {
    "id": "v918ssuf8",
    "name": "いちやまマート",
    "image": "https://image.xinu.ink/pic/data/6019/images/v918ssuf8_1746305697052_c16v9.jpg",
    "ep": 4,
    "geo": [
      35.6506,
      138.5459
    ],
    "origin": "Anitabi@concert",
    "originURL": "https://anitabi.cn/"
  },
  {
    "id": "v8sm3jcgo",
    "name": "御勅使南公園",
    "image": "https://image.xinu.ink/pic/data/6019/images/v8sm3jcgo_1746292432850.jpg",
    "ep": 4,
    "geo": [
      35.6677,
      138.4594
    ],
    "origin": "Anitabi@LovelySummer Channel",
    "originURL": "https://anitabi.cn/"
  },
  {
    "id": "v90ybe8g0",
    "name": "御勅使南公園 河岸",
    "image": "https://image.xinu.ink/pic/data/6019/images/v90ybe8g0_1746305113264_c16v9.jpg",
    "ep": 4,
    "geo": [
      35.6685,
      138.454
    ],
    "origin": "Anitabi@concert",
    "originURL": "https://anitabi.cn/"
  },
  {
    "id": "v90gh8uyf",
    "name": "南ぷす食堂",
    "image": "https://image.xinu.ink/pic/data/6019/images/v90gh8uyf_1746304142565_c16v9.jpg",
    "ep": 4,
    "geo": [
      35.6616,
      138.4399
    ],
    "origin": "Anitabi@concert",
    "originURL": "https://anitabi.cn/"
  },
  {
    "id": "v90w90o1k",
    "name": "ホームキッチンブレーメン",
    "image": "https://image.xinu.ink/pic/data/6019/images/v90w90o1k_1746304933537_c16v9.jpg",
    "ep": 4,
    "geo": [
      35.672,
      138.5241
    ],
    "origin": "Anitabi@concert",
    "originURL": "https://anitabi.cn/"
  },
  {
    "id": "v8surr39q",
    "name": "葡萄工房ワイングラス館",
    "image": "https://image.xinu.ink/pic/data/6019/images/v8surr39q_1746289239567.jpg",
    "ep": 4,
    "geo": [
      35.6792,
      138.7187
    ],
    "origin": "Anitabi@LovelySummer Channel",
    "originURL": "https://anitabi.cn/"
  },
  {
    "id": "v8tmozfv7",
    "name": "かつぬまピーチ・グレープランド",
    "image": "https://image.xinu.ink/pic/data/6019/images/v8tmozfv7_1746289845654.jpg",
    "ep": 4,
    "geo": [
      35.6752,
      138.7376
    ],
    "origin": "Anitabi@LovelySummer Channel",
    "originURL": "https://anitabi.cn/"
  },
  {
    "id": "v8w4935em",
    "name": "山県大弐銅像",
    "image": "https://image.xinu.ink/pic/data/6019/images/v8w4935em_1746294488384.jpg",
    "ep": 4,
    "geo": [
      35.6686,
      138.5193
    ],
    "origin": "Anitabi@LovelySummer Channel",
    "originURL": "https://anitabi.cn/"
  },
  {
    "id": "v8u50hupn",
    "name": "勝沼ぶどうの丘 宿泊棟",
    "image": "https://image.xinu.ink/pic/data/6019/images/v8u50hupn_1746290164612.jpg",
    "ep": 4,
    "geo": [
      35.674,
      138.7366
    ],
    "origin": "Anitabi@LovelySummer Channel",
    "originURL": "https://anitabi.cn/"
  },
  {
    "id": "v8ua3kdkb",
    "name": "天空の湯",
    "image": "https://image.xinu.ink/pic/data/6019/images/v8ua3kdkb_1746290483005.jpg",
    "ep": 4,
    "geo": [
      35.6737,
      138.7363
    ],
    "origin": "Anitabi@LovelySummer Channel",
    "originURL": "https://anitabi.cn/"
  },
  {
    "id": "v8x0m457f",
    "name": "aeon甲府",
    "image": "https://image.xinu.ink/pic/data/6019/images/v8x0m457f-1746296439295.jpg",
    "ep": 4,
    "geo": [
      35.6233,
      138.5256
    ],
    "origin": "Anitabi@蛙壶真君",
    "originURL": "https://anitabi.cn/"
  },
  {
    "id": "v8xo1ux4z",
    "name": "aeon甲府 屋上駐車場",
    "image": "https://image.xinu.ink/pic/data/6019/images/v8xo1ux4z_1746297935461_c16v9.jpg",
    "ep": 4,
    "geo": [
      35.6214,
      138.5277
    ],
    "origin": "Anitabi@concert",
    "originURL": "https://anitabi.cn/"
  },
  {
    "id": "v8zxbo0eb",
    "name": "ひなた",
    "image": "https://image.xinu.ink/pic/data/6019/images/v8zxbo0eb_1746302971598_c16v9.jpg",
    "ep": 4,
    "geo": [
      35.6733,
      138.5677
    ],
    "origin": "Anitabi@concert",
    "originURL": "https://anitabi.cn/"
  },
  {
    "id": "v91iff4nd",
    "name": "アース​測量前",
    "image": "https://image.xinu.ink/pic/data/6019/images/v91iff4nd_1746306242826_c16v9.jpg",
    "ep": 4,
    "geo": [
      35.6732,
      138.5674
    ],
    "origin": "Anitabi@concert",
    "originURL": "https://anitabi.cn/"
  },
  {
    "id": "v8zpyf89z",
    "name": "お食事処ぼんち",
    "image": "https://image.xinu.ink/pic/data/6019/images/v8zpyf89z_1746302468310_c16v9.jpg",
    "ep": 4,
    "geo": [
      35.6594,
      138.5322
    ],
    "origin": "Anitabi@concert",
    "originURL": "https://anitabi.cn/"
  },
  {
    "id": "84augr",
    "name": "お食事処ぼんち神祖道",
    "image": "https://image.xinu.ink/pic/data/6019/images/84augr_1747545603387.jpg",
    "ep": 6,
    "geo": [
      35.6596,
      138.5322
    ],
    "origin": "Anitabi@LovelySummer Channel",
    "originURL": "https://anitabi.cn/"
  },
  {
    "id": "84lh0k",
    "name": "竜王新町",
    "image": "https://image.xinu.ink/pic/data/6019/images/84lh0k_1747545632424.jpg",
    "ep": 6,
    "geo": [
      35.6666,
      138.5177
    ],
    "origin": "Anitabi@LovelySummer Channel",
    "originURL": "https://anitabi.cn/"
  },
  {
    "id": "850sru",
    "name": "森沢自転車店",
    "image": "https://image.xinu.ink/pic/data/6019/images/850sru_1747545649105.jpg",
    "ep": 6,
    "geo": [
      35.6811,
      138.539
    ],
    "origin": "Anitabi@LovelySummer Channel",
    "originURL": "https://anitabi.cn/"
  },
  {
    "id": "vgitcilre",
    "cn": "萌木の村",
    "name": 174,
    "image": "https://image.xinu.ink/pic/data/6019/images/vgitcilre_1746898948531.jpg",
    "ep": 5,
    "geo": [
      35.9132,
      138.4429
    ],
    "origin": "Anitabi@LovelySummer Channel",
    "originURL": "https://anitabi.cn/"
  },
  {
    "id": "vglu04g8v",
    "cn": "萌木の村ROCK",
    "name": 174,
    "image": "https://image.xinu.ink/pic/data/6019/images/vglu04g8v_1746898997872.jpg",
    "ep": 5,
    "geo": [
      35.9137,
      138.4427
    ],
    "origin": "Anitabi@LovelySummer Channel",
    "originURL": "https://anitabi.cn/"
  },
  {
    "id": "vgjzduvks",
    "name": "清里ハム",
    "image": "https://image.xinu.ink/pic/data/6019/images/vgjzduvks_1746897829506.jpg",
    "ep": 5,
    "geo": [
      35.8994,
      138.437
    ],
    "origin": "Anitabi@LovelySummer Channel",
    "originURL": "https://anitabi.cn/"
  },
  {
    "id": "vgl1e7xap",
    "name": "全家",
    "image": "https://image.xinu.ink/pic/data/6019/images/vgl1e7xap_1746897272369.jpg",
    "ep": 5,
    "geo": [
      35.9185,
      138.4366
    ],
    "origin": "Anitabi@LovelySummer Channel",
    "originURL": "https://anitabi.cn/"
  },
  {
    "id": "vgkyue2nu",
    "name": "ミルクポット",
    "image": "https://image.xinu.ink/pic/data/6019/images/vgkyue2nu_1746897116879.jpg",
    "ep": 5,
    "geo": [
      35.9183,
      138.436
    ],
    "origin": "Anitabi@LovelySummer Channel",
    "originURL": "https://anitabi.cn/"
  },
  {
    "id": "vgjpymy8y",
    "name": "八ヶ岳PA下り",
    "image": "https://image.xinu.ink/pic/data/6019/images/vgjpymy8y_1746896846559.jpg",
    "ep": 5,
    "geo": [
      35.8446,
      138.3644
    ],
    "origin": "Anitabi@LovelySummer Channel",
    "originURL": "https://anitabi.cn/"
  },
  {
    "id": "vgldf7ql1",
    "name": "サンメドウズ清里 清里テラス",
    "image": "https://image.xinu.ink/pic/data/6019/images/vgldf7ql1_1746898001429.jpg",
    "ep": 5,
    "geo": [
      35.9509,
      138.4013
    ],
    "origin": "Anitabi@LovelySummer Channel",
    "originURL": "https://anitabi.cn/"
  },
  {
    "id": "vgj1j73wb",
    "cn": "清里站",
    "name": "清里",
    "image": "https://image.xinu.ink/pic/data/6019/images/vgj1j73wb_1746896828150.jpg",
    "ep": 5,
    "geo": [
      35.919,
      138.4366
    ],
    "origin": "Anitabi@LovelySummer Channel",
    "originURL": "https://anitabi.cn/"
  },
  {
    "id": "vgm9rg161",
    "cn": "新宿哥斯拉",
    "name": 215,
    "image": "https://image.xinu.ink/pic/data/6019/images/vgm9rg161_1746899950602.jpg",
    "ep": 5,
    "geo": [
      35.6951,
      139.7017
    ],
    "origin": "Anitabi@LovelySummer Channel",
    "originURL": "https://anitabi.cn/"
  },
  {
    "id": "80zlgi",
    "name": "滝見の湯",
    "image": "https://image.xinu.ink/pic/data/6019/images/80zlgi_1747546947419.jpg",
    "ep": 6,
    "geo": [
      36.0171,
      138.5658
    ],
    "origin": "Anitabi@LovelySummer Channel",
    "originURL": "https://anitabi.cn/"
  },
  {
    "id": "819bfs",
    "name": "大弛峠",
    "image": "https://image.xinu.ink/pic/data/6019/images/819bfs_1747546879098.jpg",
    "ep": 6,
    "geo": [
      35.873,
      138.6631
    ],
    "origin": "Anitabi@LovelySummer Channel",
    "originURL": "https://anitabi.cn/"
  },
  {
    "id": "81h21l",
    "cn": "甲斐奈神社元宮",
    "name": "",
    "image": "https://image.xinu.ink/pic/data/6019/images/81h21l_1747546111716.jpg",
    "ep": 6,
    "geo": [
      35.6673,
      138.5801
    ],
    "origin": "Anitabi@LovelySummer Channel",
    "originURL": "https://anitabi.cn/"
  },
  {
    "id": "8uqi5a",
    "name": "Tokojimachi",
    "image": "https://image.xinu.ink/pic/data/6019/images/8uqi5a_1747545706825.jpg",
    "ep": 6,
    "geo": [
      35.6707,
      138.581
    ],
    "origin": "Anitabi@LovelySummer Channel",
    "originURL": "https://anitabi.cn/"
  },
  {
    "id": "82h7h2",
    "cn": "甲斐市下今井上町道祖神",
    "name": 226,
    "image": "https://image.xinu.ink/pic/data/6019/images/82h7h2_1747545588671.jpg",
    "ep": 6,
    "geo": [
      35.6837,
      138.4923
    ],
    "origin": "Anitabi@LovelySummer Channel",
    "originURL": "https://anitabi.cn/"
  },
  {
    "id": "85ffle",
    "name": "県立博物館",
    "image": "https://image.xinu.ink/pic/data/6019/images/85ffle_1747545434894.jpg",
    "ep": 6,
    "geo": [
      35.6405,
      138.6485
    ],
    "origin": "Anitabi@LovelySummer Channel",
    "originURL": "https://anitabi.cn/"
  },
  {
    "id": "816w1h",
    "cn": "Hottarakashi温泉",
    "name": "ほったらかし​温泉",
    "image": "https://image.xinu.ink/pic/data/6019/images/816w1h_1747546769651.jpg",
    "ep": 6,
    "geo": [
      35.7062,
      138.6521
    ],
    "origin": "Anitabi@LovelySummer Channel",
    "originURL": "https://anitabi.cn/"
  },
  {
    "id": "86ehez",
    "name": "一刀斎",
    "image": "https://image.xinu.ink/pic/data/6019/images/86ehez_1747546419198.jpg",
    "ep": 6,
    "geo": [
      35.6624,
      138.5703
    ],
    "origin": "Anitabi@LovelySummer Channel",
    "originURL": "https://anitabi.cn/"
  },
  {
    "id": "86ihk5",
    "name": "印度キッチン",
    "image": "https://image.xinu.ink/pic/data/6019/images/86ihk5_1747546555465.jpg",
    "ep": 6,
    "geo": [
      35.653,
      138.5469
    ],
    "origin": "Anitabi@LovelySummer Channel",
    "originURL": "https://anitabi.cn/"
  },
  {
    "id": "ithug3",
    "name": "山梨水晶本店",
    "image": "https://image.xinu.ink/pic/data/6019/images/ithug3_1748148295364.jpg",
    "ep": 7,
    "geo": [
      35.3614,
      138.4524
    ],
    "origin": "Anitabi@月即别",
    "originURL": "https://anitabi.cn/"
  },
  {
    "id": "ititye",
    "name": "ゆたか屋",
    "image": "https://image.xinu.ink/pic/data/6019/images/ititye_1748148335442.jpg",
    "ep": 7,
    "geo": [
      35.361,
      138.4522
    ],
    "origin": "Anitabi@月即别",
    "originURL": "https://anitabi.cn/"
  },
  {
    "id": "itjmub",
    "name": "ぶどう屋",
    "image": "https://image.xinu.ink/pic/data/6019/images/itjmub_1748148372549.jpg",
    "ep": 7,
    "geo": [
      35.3614,
      138.4522
    ],
    "origin": "Anitabi@月即别",
    "originURL": "https://anitabi.cn/"
  },
  {
    "id": "ouj5y9",
    "name": "身延駅前しょうにん",
    "image": "https://image.xinu.ink/pic/data/6019/images/ouj5y9_1748512834120.jpg",
    "ep": 7,
    "geo": [
      35.3619,
      138.4523
    ],
    "origin": "Anitabi@LovelySummer Channel",
    "originURL": "https://anitabi.cn/"
  },
  {
    "id": "itzmyd",
    "name": "下部ホテル",
    "image": "https://image.xinu.ink/pic/data/6019/images/itzmyd_1748149129547.jpg",
    "ep": 7,
    "geo": [
      35.4255,
      138.4712
    ],
    "origin": "Anitabi@月即别",
    "originURL": "https://anitabi.cn/"
  },
  {
    "id": "ov0ykk",
    "name": "下部​温泉​ボロネーゼ",
    "image": "https://image.xinu.ink/pic/data/6019/images/ov0ykk_1748513654553.jpg",
    "ep": 7,
    "geo": [
      35.4252,
      138.4703
    ],
    "origin": "Anitabi@LovelySummer Channel",
    "originURL": "https://anitabi.cn/"
  },
  {
    "id": "iu2zrg",
    "name": "丸一食堂",
    "image": "https://image.xinu.ink/pic/data/6019/images/iu2zrg_1748149276803.jpg",
    "ep": 7,
    "geo": [
      35.4252,
      138.4722
    ],
    "origin": "Anitabi@月即别",
    "originURL": "https://anitabi.cn/"
  },
  {
    "id": "iu7epx",
    "name": "富士川​クラフト​パーク",
    "image": "https://image.xinu.ink/pic/data/6019/images/iu7epx_1748149482419.jpg",
    "ep": 7,
    "geo": [
      35.4191,
      138.4377
    ],
    "origin": "Anitabi@月即别",
    "originURL": "https://anitabi.cn/"
  },
  {
    "id": "iua4c6",
    "name": "麺や響",
    "image": "https://image.xinu.ink/pic/data/6019/images/iua4c6_1748149607079.jpg",
    "ep": 7,
    "geo": [
      35.4339,
      138.4414
    ],
    "origin": "Anitabi@月即别",
    "originURL": "https://anitabi.cn/"
  },
  {
    "id": "iue5m2",
    "name": "セルバみのぶ店",
    "image": "https://image.xinu.ink/pic/data/6019/images/iue5m2_1748149804676.jpg",
    "ep": 7,
    "geo": [
      35.4328,
      138.4414
    ],
    "origin": "Anitabi@月即别",
    "originURL": "https://anitabi.cn/"
  },
  {
    "id": "iug567",
    "name": "園林　カレー",
    "image": "https://image.xinu.ink/pic/data/6019/images/iug567_1748149891951.jpg",
    "ep": 7,
    "geo": [
      35.3768,
      138.4252
    ],
    "origin": "Anitabi@月即别",
    "originURL": "https://anitabi.cn/"
  },
  {
    "id": "ovww24",
    "cn": "久遠寺 三门",
    "name": "身延山久遠寺",
    "image": "https://image.xinu.ink/pic/data/6019/images/ovww24_1748515143902.jpg",
    "ep": 7,
    "geo": [
      35.3819,
      138.4249
    ],
    "origin": "Anitabi@LovelySummer Channel",
    "originURL": "https://anitabi.cn/"
  },
  {
    "id": "ovz4cu",
    "cn": "觉林坊",
    "name": "身延山久遠寺",
    "image": "https://image.xinu.ink/pic/data/6019/images/ovz4cu_1748515256784.jpg",
    "ep": 7,
    "geo": [
      35.3796,
      138.4273
    ],
    "origin": "Anitabi@LovelySummer Channel",
    "originURL": "https://anitabi.cn/"
  },
  {
    "id": "iv4ccv",
    "name": "電電宮",
    "image": "https://image.xinu.ink/pic/data/6019/images/iv4ccv_1748151114086.jpg",
    "ep": 7,
    "geo": [
      35.0097,
      135.678
    ],
    "origin": "Anitabi@月即别",
    "originURL": "https://anitabi.cn/"
  },
  {
    "id": "owd1xf",
    "cn": "久遠寺缆车旁",
    "name": "久遠寺",
    "image": "https://image.xinu.ink/pic/data/6019/images/owd1xf_1748515903738.jpg",
    "ep": 7,
    "geo": [
      35.3836,
      138.4242
    ],
    "origin": "Anitabi@LovelySummer Channel",
    "originURL": "https://anitabi.cn/"
  },
  {
    "id": "owjxk2",
    "cn": "洗心洞",
    "name": 338,
    "image": "https://image.xinu.ink/pic/data/6019/images/owjxk2_1748516218577.jpg",
    "ep": 7,
    "geo": [
      35.382,
      138.4202
    ],
    "origin": "Anitabi@LovelySummer Channel",
    "originURL": "https://anitabi.cn/"
  },
  {
    "id": "owr23a",
    "name": "南側展望台",
    "image": "https://image.xinu.ink/pic/data/6019/images/owr23a_1748516618070.jpg",
    "ep": 7,
    "geo": [
      35.3967,
      138.4179
    ],
    "origin": "Anitabi@LovelySummer Channel",
    "originURL": "https://anitabi.cn/"
  },
  {
    "id": "owtac4",
    "name": "身延​山奥​之​院​思​親​閣​本堂",
    "image": "https://image.xinu.ink/pic/data/6019/images/owtac4_1748516655241.jpg",
    "ep": 7,
    "geo": [
      35.3973,
      138.417
    ],
    "origin": "Anitabi@LovelySummer Channel",
    "originURL": "https://anitabi.cn/"
  },
  {
    "id": "vgiwgxgwd",
    "cn": "八岳高原大桥",
    "name": "八ヶ岳高原大橋",
    "image": "https://image.xinu.ink/pic/data/6019/images/vgiwgxgwd-1746892786092.jpg",
    "ep": null,
    "geo": [
      35.8919,
      138.4231
    ],
    "origin": "Anitabi@蛙壶真君",
    "originURL": "https://anitabi.cn/"
  },
  {
    "id": "vgmf21ox8",
    "name": "芳文社",
    "image": "https://image.xinu.ink/pic/data/6019/images/vgmf21ox8_1746900277737.jpg",
    "geo": [
      35.7027,
      139.7515
    ],
    "origin": "Anitabi@LovelySummer Channel",
    "originURL": "https://anitabi.cn/"
  }
]